ticapsoriginal_sitemaps2txt/__init__.py
ticapsoriginal_sitemaps2txt-1.0.0.dist-info/LICENSE
ticapsoriginal_sitemaps2txt-1.0.0.dist-info/METADATA
ticapsoriginal_sitemaps2txt-1.0.0.dist-info/WHEEL
ticapsoriginal_sitemaps2txt-1.0.0.dist-info/top_level.txt
ticapsoriginal_sitemaps2txt-1.0.0.dist-info/RECORD
